kkplot/__init__.py
kkplot-0.0.2.dist-info/LICENSE
kkplot-0.0.2.dist-info/METADATA
kkplot-0.0.2.dist-info/WHEEL
kkplot-0.0.2.dist-info/top_level.txt
kkplot-0.0.2.dist-info/RECORD
