Metadata-Version: 2.1
Name: kkplot
Version: 0.0.2
Summary: Helpful additions to matplotlib.
Home-page: https://github.com/kkrizka/kkplot
Author: Karol Krizka
Author-email: kkrizka@gmail.com
Classifier: Programming Language :: Python :: 3
Classifier: License :: OSI Approved :: GNU General Public License v3 (GPLv3)
Classifier: Operating System :: OS Independent
License-File: LICENSE
Requires-Dist: matplotlib
Requires-Dist: numpy
Requires-Dist: scipy
